flask_replit_auth/__init__.py
flask_replit_auth-1.1.1.dist-info/LICENSE
flask_replit_auth-1.1.1.dist-info/METADATA
flask_replit_auth-1.1.1.dist-info/WHEEL
flask_replit_auth-1.1.1.dist-info/top_level.txt
flask_replit_auth-1.1.1.dist-info/RECORD
