Metadata-Version: 2.1
Name: flask-replit-auth
Version: 1.1.1
Summary: Brings replit auth to flask.
Home-page: https://replit.com/@EpicCodeWizard/flaskreplitauth
Author: EpicCodeWizard
Author-email: epiccodewizard@gmail.com
License: UNKNOWN
Platform: UNKNOWN
Classifier: Programming Language :: Python :: 3
Classifier: License :: OSI Approved :: MIT License
Classifier: Operating System :: OS Independent
Requires-Dist: requests
Requires-Dist: flask
